easy_plot_beamline/__init__.py
easy_plot_beamline/cli.py
easy_plot_beamline/plotting.py
easy_plot_beamline/version.py
easy_plot_beamline-0.1.0.dist-info/licenses/AUTHORS.rst
easy_plot_beamline-0.1.0.dist-info/licenses/LICENSE.rst
easy_plot_beamline-0.1.0.dist-info/METADATA
easy_plot_beamline-0.1.0.dist-info/WHEEL
easy_plot_beamline-0.1.0.dist-info/entry_points.txt
easy_plot_beamline-0.1.0.dist-info/top_level.txt
easy_plot_beamline-0.1.0.dist-info/RECORD
