Metadata-Version: 2.4
Name: easy-plot-beamline
Version: 0.1.0
Summary: Easily plot and visualize two-column data on-the-fly.
Author-email: Caden Myers <cjm2304@columbia.edu>
Maintainer-email: Caden Myers <cjm2304@columbia.edu>
Project-URL: Homepage, https://github.com/cadenmyers13/easy-plot-beamline/
Project-URL: Issues, https://github.com/cadenmyers13/easy-plot-beamline/issues/
Keywords: diffraction,PDF,X-ray,neutron
Classifier: Development Status :: 5 - Production/Stable
Classifier: Environment :: Console
Classifier: Intended Audience :: Developers
Classifier: Intended Audience :: Science/Research
Classifier: License :: OSI Approved :: BSD License
Classifier: Operating System :: MacOS :: MacOS X
Classifier: Operating System :: Microsoft :: Windows
Classifier: Operating System :: POSIX
Classifier: Operating System :: Unix
Classifier: Programming Language :: Python :: 3.11
Classifier: Programming Language :: Python :: 3.12
Classifier: Programming Language :: Python :: 3.13
Classifier: Programming Language :: Python :: 3.14
Classifier: Topic :: Scientific/Engineering :: Physics
Classifier: Topic :: Scientific/Engineering :: Chemistry
Requires-Python: <3.15,>=3.11
License-File: LICENSE.rst
License-File: AUTHORS.rst
Requires-Dist: numpy
Requires-Dist: matplotlib
Requires-Dist: diffpy.utils
Dynamic: license-file
